Metadata-Version: 1.1
Name: server-dev
Version: 1.1.1
Summary: Python wrapper for vCenter Management API 6.5.
Home-page: https://pypi.org/project/server-dev/
Author: Caidence Pyle
Author-email: caiden.pyle@netapp.com
License: MIT
Project-URL: Documentation, https://caidenpyle.com/tutorials/serverdev/main.html
Keywords: api esx esxi vmware
Platform: UNKNOWN
Classifier: Development Status :: 4 - Beta
Classifier: Operating System :: POSIX :: Linux
Classifier: Operating System :: Microsoft :: Windows
Classifier: Intended Audience :: Developers
Classifier: Intended Audience :: Information Technology
Classifier: Intended Audience :: System Administrators
Classifier: Topic :: Utilities
Classifier: Topic :: System :: Systems Administration
Classifier: Topic :: Software Development :: Libraries :: Application Frameworks
Classifier: License :: Freeware
Classifier: Programming Language :: Python :: 2
Classifier: Programming Language :: Python :: 3
